viztracer/__init__.py
viztracer/__main__.py
viztracer/attach.py
viztracer/cellmagic.py
viztracer/code_monkey.py
viztracer/decorator.py
viztracer/event_base.py
viztracer/functree.py
viztracer/main.py
viztracer/patch.py
viztracer/report_builder.py
viztracer/snaptrace.cp313-win_amd64.pyd
viztracer/snaptrace.pyi
viztracer/util.py
viztracer/vcompressor.cp313-win_amd64.pyd
viztracer/vcompressor.pyi
viztracer/viewer.py
viztracer/vizcounter.py
viztracer/vizevent.py
viztracer/vizlogging.py
viztracer/vizobject.py
viztracer/vizplugin.py
viztracer/viztracer.py
viztracer/attach_process/LICENSE
viztracer/attach_process/__init__.py
viztracer/attach_process/add_code_to_python_process.py
viztracer/attach_process/attach_x86.dll
viztracer/attach_process/inject_dll_amd64.exe
viztracer/attach_process/run_code_on_dllmain_amd64.dll
viztracer/attach_process/run_code_on_dllmain_x86.dll
viztracer/attach_process/linux_and_mac/lldb_prepare.py
viztracer/html/flamegraph.html
viztracer/html/trace_viewer_embedder.html
viztracer/html/trace_viewer_full.html
viztracer/modules/eventnode.c
viztracer/modules/eventnode.h
viztracer/modules/pythoncapi_compat.h
viztracer/modules/quicktime.c
viztracer/modules/quicktime.h
viztracer/modules/snaptrace.c
viztracer/modules/snaptrace.h
viztracer/modules/snaptrace_member.c
viztracer/modules/util.c
viztracer/modules/util.h
viztracer/modules/vcompressor/vc_dump.c
viztracer/modules/vcompressor/vc_dump.h
viztracer/modules/vcompressor/vcompressor.c
viztracer/modules/vcompressor/vcompressor.h
viztracer/web_dist/LICENSE
viztracer/web_dist/index.html
viztracer/web_dist/service_worker.js
viztracer/web_dist/trace_processor
viztracer/web_dist/v52.0-6b9586def/engine_bundle.js
viztracer/web_dist/v52.0-6b9586def/frontend_bundle.js
viztracer/web_dist/v52.0-6b9586def/index.html
viztracer/web_dist/v52.0-6b9586def/manifest.json
viztracer/web_dist/v52.0-6b9586def/perfetto.css
viztracer/web_dist/v52.0-6b9586def/stdlib_docs.json
viztracer-1.1.1.dist-info/licenses/LICENSE
viztracer-1.1.1.dist-info/licenses/NOTICE.txt
viztracer-1.1.1.dist-info/METADATA
viztracer-1.1.1.dist-info/WHEEL
viztracer-1.1.1.dist-info/entry_points.txt
viztracer-1.1.1.dist-info/top_level.txt
viztracer-1.1.1.dist-info/RECORD
