Metadata-Version: 2.4
Name: viztracer
Version: 1.1.1
Summary: A debugging and profiling tool that can trace and visualize python code execution
Author-email: Tian Gao <gaogaotiantian@hotmail.com>
License-Expression: Apache-2.0
Project-URL: Homepage, https://github.com/gaogaotiantian/viztracer
Project-URL: Documentation, https://viztracer.readthedocs.io
Classifier: Development Status :: 5 - Production/Stable
Classifier: Programming Language :: Python :: 3.10
Classifier: Programming Language :: Python :: 3.11
Classifier: Programming Language :: Python :: 3.12
Classifier: Programming Language :: Python :: 3.13
Classifier: Programming Language :: Python :: 3.14
Classifier: Programming Language :: Python :: Free Threading
Classifier: Programming Language :: Python :: Free Threading :: 3 - Stable
Classifier: Intended Audience :: Developers
Classifier: Operating System :: MacOS
Classifier: Operating System :: POSIX :: Linux
Classifier: Operating System :: Microsoft :: Windows
Classifier: Topic :: Software Development :: Quality Assurance
Classifier: Topic :: Software Development :: Bug Tracking
Classifier: Topic :: System :: Logging
Requires-Python: >=3.10
License-File: LICENSE
License-File: NOTICE.txt
Requires-Dist: objprint>=0.3.0
Provides-Extra: full
Requires-Dist: orjson; extra == "full"
Dynamic: license-file
